pytest_idempotent/__init__.py
pytest_idempotent/py.typed
pytest_idempotent-1.3.1.dist-info/LICENSE
pytest_idempotent-1.3.1.dist-info/METADATA
pytest_idempotent-1.3.1.dist-info/WHEEL
pytest_idempotent-1.3.1.dist-info/entry_points.txt
pytest_idempotent-1.3.1.dist-info/top_level.txt
pytest_idempotent-1.3.1.dist-info/RECORD
