Metadata-Version: 2.1
Name: pytest-idempotent
Version: 1.3.1
Summary: Pytest plugin for testing function idempotence.
Home-page: https://github.com/tyleryep/pytest-idempotent
Author: Tyler Yep
Author-email: tyep@cs.stanford.edu
License: MIT
Classifier: License :: OSI Approved :: MIT License
Classifier: Operating System :: OS Independent
Classifier: Framework :: Pytest
Classifier: Programming Language :: Python :: 3
Classifier: Programming Language :: Python :: 3 :: Only
Classifier: Programming Language :: Python :: 3.7
Classifier: Programming Language :: Python :: 3.8
Classifier: Programming Language :: Python :: 3.9
Classifier: Programming Language :: Python :: 3.10
Classifier: Programming Language :: Python :: 3.11
Requires-Python: >=3.7
License-File: LICENSE
